langlight/__init__.py
langlight/_expect.py
langlight/_internal/__init__.py
langlight/_internal/_aiter.py
langlight/_internal/_background_thread.py
langlight/_internal/_beta_decorator.py
langlight/_internal/_compressed_traces.py
langlight/_internal/_constants.py
langlight/_internal/_edit_distance.py
langlight/_internal/_embedding_distance.py
langlight/_internal/_multipart.py
langlight/_internal/_operations.py
langlight/_internal/_orjson.py
langlight/_internal/_patch.py
langlight/_internal/_serde.py
langlight/anonymizer.py
langlight/async_client.py
langlight/beta/__init__.py
langlight/beta/_evals.py
langlight/cli/README.md
langlight/client.py
langlight/evaluation/__init__.py
langlight/evaluation/_arunner.py
langlight/evaluation/_name_generation.py
langlight/evaluation/_runner.py
langlight/evaluation/evaluator.py
langlight/evaluation/integrations/__init__.py
langlight/evaluation/integrations/_langchain.py
langlight/evaluation/integrations/test.excalidraw.png
langlight/evaluation/llm_evaluator.py
langlight/evaluation/string_evaluator.py
langlight/middleware.py
langlight/py.typed
langlight/pytest_plugin.py
langlight/run_helpers.py
langlight/run_trees.py
langlight/schemas.py
langlight/testing/__init__.py
langlight/testing/_internal.py
langlight/utils.py
langlight/wrappers/__init__.py
langlight/wrappers/_anthropic.py
langlight/wrappers/_openai.py
langlight-0.3.13.dist-info/entry_points.txt
langlight-0.3.13.dist-info/METADATA
langlight-0.3.13.dist-info/WHEEL
langlight-0.3.13.dist-info/RECORD
