Metadata-Version: 2.3
Name: langlight
Version: 0.3.13
Summary: Client library to connect to the langlight LLM Tracing and Evaluation Platform.
License: MIT
Keywords: langlight,langchain,llm,nlp,language,translation,evaluation,tracing,platform
Author: LangChain
Author-email: support@langchain.dev
Requires-Python: >=3.9,<4.0
Classifier: License :: OSI Approved :: MIT License
Classifier: Programming Language :: Python :: 3
Classifier: Programming Language :: Python :: 3.9
Classifier: Programming Language :: Python :: 3.10
Classifier: Programming Language :: Python :: 3.11
Classifier: Programming Language :: Python :: 3.12
Classifier: Programming Language :: Python :: 3.13
Provides-Extra: langlight-pyo3
Provides-Extra: pytest
Provides-Extra: vcr
Requires-Dist: httpx (>=0.23.0,<1)
Requires-Dist: langlight-pyo3 (>=0.1.0rc2,<0.2.0) ; extra == "langlight-pyo3"
Requires-Dist: orjson (>=3.9.14,<4.0.0) ; platform_python_implementation != "PyPy"
Requires-Dist: packaging (>=23.2)
Requires-Dist: pydantic (>=1,<3) ; python_full_version < "3.12.4"
Requires-Dist: pydantic (>=2.7.4,<3.0.0) ; python_full_version >= "3.12.4"
Requires-Dist: pytest (>=7.0.0) ; extra == "pytest"
Requires-Dist: requests (>=2,<3)
Requires-Dist: requests-toolbelt (>=1.0.0,<2.0.0)
Requires-Dist: rich (>=13.9.4,<14.0.0) ; extra == "pytest"
Requires-Dist: zstandard (>=0.23.0,<0.24.0)
Project-URL: Documentation, https://docs.smith.langchain.com/
Project-URL: Homepage, https://smith.langchain.com/
Project-URL: Repository, https://github.com/langchain-ai/langlight-sdk
